MANIFEST.in
README.md
setup.py
devotionals/__init__.py
devotionals/admin.py
devotionals/forms.py
devotionals/managers.py
devotionals/models.py
devotionals/tests.py
devotionals/urls.py
devotionals/views.py
django_devotionals.egg-info/PKG-INFO
django_devotionals.egg-info/SOURCES.txt
django_devotionals.egg-info/dependency_links.txt
django_devotionals.egg-info/not-zip-safe
django_devotionals.egg-info/top_level.txt