Metadata-Version: 1.0
Name: django-devotionals
Version: 0.1.0
Summary: An application for managing daily devotionals.
Home-page: http://github.com/powellc/django-devotionals
Author: Colin Powell
Author-email: colin@onecardinal.com
License: BSD
Platform: UNKNOWN
Classifier: Development Status :: 4 - Beta
Classifier: Environment :: Web Environment
Classifier: Intended Audience :: Developers
Classifier: License :: OSI Approved :: BSD License
Classifier: Operating System :: OS Independent
Classifier: Programming Language :: Python
Classifier: Framework :: Django
